clc_export_tool/__init__.py
clc_export_tool-0.0.14.dist-info/DESCRIPTION.rst
clc_export_tool-0.0.14.dist-info/METADATA
clc_export_tool-0.0.14.dist-info/RECORD
clc_export_tool-0.0.14.dist-info/WHEEL
clc_export_tool-0.0.14.dist-info/entry_points.txt
clc_export_tool-0.0.14.dist-info/metadata.json
clc_export_tool-0.0.14.dist-info/top_level.txt
